{
    "628298729405022216": {
        "currencies": {
            "ZlPEJfBvvc68Gmd2Hcd9l": {
                "item": "ZlPEJfBvvc68Gmd2Hcd9l",
                "amount": 14952.1
            },
            "b4kXfz14I6Dg-2HuJN65Z": {
                "item": "b4kXfz14I6Dg-2HuJN65Z",
                "amount": 235
            }
        },
        "inventory": {
            "Nt4GT7m_M1b-3EeoxbfWC": {
                "item": {
                    "id": "Nt4GT7m_M1b-3EeoxbfWC",
                    "shopId": "T2ZDGLBOCTvFjxlsfg5Ku"
                },
                "amount": 4
            },
            "3z4IBSyuLcYk9AYFXQhMN": {
                "item": {
                    "id": "3z4IBSyuLcYk9AYFXQhMN",
                    "shopId": "O8jl-dKcMa1q6xb1h4kMI"
                },
                "amount": 3
            },
            "PXMuiYB49HX9TrPvTLzKA": {
                "item": {
                    "id": "PXMuiYB49HX9TrPvTLzKA",
                    "shopId": "O8jl-dKcMa1q6xb1h4kMI"
                },
                "amount": 19
            },
            "nrxAyQIWlZyFpXhQqLfwT": {
                "item": {
                    "id": "nrxAyQIWlZyFpXhQqLfwT",
                    "shopId": "O8jl-dKcMa1q6xb1h4kMI"
                },
                "amount": 1
            },
            "a0TJ56AwvipDIo2o6HzBZ": {
                "item": {
                    "id": "a0TJ56AwvipDIo2o6HzBZ",
                    "shopId": "O8jl-dKcMa1q6xb1h4kMI"
                },
                "amount": 1
            },
            "G4mvJMp6NtefurANxYSUX": {
                "item": {
                    "id": "G4mvJMp6NtefurANxYSUX",
                    "shopId": "T2ZDGLBOCTvFjxlsfg5Ku"
                },
                "amount": 1
            },
            "z5QSfmPMAEZ4swt6P9RgN": {
                "item": {
                    "id": "z5QSfmPMAEZ4swt6P9RgN",
                    "shopId": "T2ZDGLBOCTvFjxlsfg5Ku"
                },
                "amount": 1
            },
            "J-fAH8DQfwtRRUjtMqKMq": {
                "item": {
                    "id": "J-fAH8DQfwtRRUjtMqKMq",
                    "shopId": "O8jl-dKcMa1q6xb1h4kMI"
                },
                "amount": 1
            },
            "yQRi-X-EG4pLmVcoheUGZ": {
                "item": {
                    "id": "yQRi-X-EG4pLmVcoheUGZ",
                    "shopId": "O8jl-dKcMa1q6xb1h4kMI"
                },
                "amount": 1
            },
            "CSPbI59YmQcI8QiEt8IqA": {
                "item": {
                    "id": "CSPbI59YmQcI8QiEt8IqA",
                    "shopId": "O8jl-dKcMa1q6xb1h4kMI"
                },
                "amount": 1
            },
            "zUzsnvPjgm-rtNySeBevE": {
                "item": {
                    "id": "zUzsnvPjgm-rtNySeBevE",
                    "shopId": "fvqtk30qXxxsnLHog2xMp"
                },
                "amount": 6
            },
            "0gH15q970O-n4CYQBi6ft": {
                "item": {
                    "id": "0gH15q970O-n4CYQBi6ft",
                    "shopId": "fvqtk30qXxxsnLHog2xMp"
                },
                "amount": 2
            }
        }
    },
    "1109842206832988272": {
        "currencies": {
            "ZlPEJfBvvc68Gmd2Hcd9l": {
                "item": "ZlPEJfBvvc68Gmd2Hcd9l",
                "amount": 0
            }
        },
        "inventory": {}
    }
}